{
  "code": "slabstacksetter",
  "class": "ItemSlabContentSetter",
  "attributes": { "slabstackdb": true },
  "shape": { "base": "item/tool/ballodirt" },
  "textures": { "all": { "base": "game:block/metal/plate/copper" } },
  "creativeinventory": { "general": ["*"], "stonequarry": ["*"] },
  "heldTpUseAnimation": "axechop",
  "heldTpHitAnimation": "axechop",
  "fpHandTransform": {
    "translation": { "x": 0, "y": 0.6, "z": 1.2 },
    "rotation": { "x": 180, "y": 160, "z": -95 },
    "origin": { "x": 0, "y": 0, "z": 0 },
    "scale": 2.14
  },
  "tpHandTransform": {
    "translation": { "x": -0.167, "y": -0.09, "z": 0.037 },
    "rotation": { "x": 90, "y": 25, "z": 9 },
    "origin": { "x": 0, "y": 0, "z": 0 },
    "scale": 0.85
  },
  "guiTransform": {
    "translation": { "x": 4, "y": 3, "z": 0 },
    "rotation": { "x": -10, "y": -42, "z": 19 },
    "origin": { "x": 0, "y": 0, "z": 0 },
    "scale": 4.66
  }
}
